kirbacterai/__init__.py
kirbacterai/kirbacterai.py
kirbacterai/objects.py
kirbacterai-0.0.3.dist-info/METADATA
kirbacterai-0.0.3.dist-info/WHEEL
kirbacterai-0.0.3.dist-info/top_level.txt
kirbacterai-0.0.3.dist-info/RECORD
