Metadata-Version: 2.1
Name: kirbacterai
Version: 0.0.3
Home-page: https://github.com/KirbyRedius/KirbacterAI
Author: KirbyRedius
Keywords: character,characterai,beta.character.ai,c.ai,kirbacter,api
Classifier: Programming Language :: Python :: 3
Requires-Dist: pyppeteer (==1.0.2)
Requires-Dist: pyppeteer-stealth (==2.7.4)
